{
  "statusInfo": {
    "statusCode": 200,
    "statusMessage": "success",
    "errorMessage": ""
  },
  "responseData": [
    {
      "type": "COMPETENCY",
      "id": "CID0214",
      "name": "Planning and Organising resources",
      "description": "Covers organising, prioritising and planning time and resources, be they human, physical or financial. This may include planning and organising one’s own work;\nplanning work for others on day to day tasks or on projects; carrying out operational planning; and planning for coming years. ",
      "status": "VERIFIED",
      "source": "ISTM",
      "additionalProperties": {
        "competencyType": "Behavioural",
        "cod": "NPA",
        "competencyArea": "Administration and Management"
      }
    },
    {
      "type": "COMPETENCY",
      "id": "CID029",
      "name": "Design Thinking",
      "description": "Thinking Capability in a Design Process...",
      "status": "UNVERIFIED",
      "source": "ISTM",
      "additionalProperties": {
        "competencyType": "Behavioural",
        "cod": "FRAC",
        "competencyArea": "Social Studies"
      }
    },
    {
      "type": "COMPETENCY",
      "id": "CID0245",
      "name": "Agriculture",
      "description": "competency",
      "status": "UNVERIFIED",
      "source": "ISTM",
      "additionalProperties": {
        "competencyType": "Behavioural",
        "cod": "iGOT",
        "competencyArea": "Research and Development"
      }
    },
    {
      "type": "COMPETENCY",
      "id": "CID08",
      "name": "Cthree",
      "description": "Description",
      "status": "UNVERIFIED",
      "source": "ISTM",
      "additionalProperties": {
        "competencyType": "Functional",
        "cod": "NACIN",
        "competencyArea": "Political Sciences"
      }
    },
    {
      "type": "COMPETENCY",
      "id": "CID0256",
      "name": "IT ",
      "description": "description-",
      "status": "UNVERIFIED",
      "source": "ISTM",
      "additionalProperties": {
        "competencyType": "Behavioural",
        "cod": "NPA",
        "competencyArea": "Level 1"
      }
    },
    {
      "type": "COMPETENCY",
      "id": "CID0215",
      "name": "Sales",
      "description": "sales:",
      "status": "UNVERIFIED",
      "source": "ISTM",
      "additionalProperties": {
        "competencyType": "Domain",
        "cod": "JPAL",
        "competencyArea": "Management"
      }
    },
    {
      "type": "COMPETENCY",
      "id": "CID0224",
      "name": "Management ",
      "description": "Manage office works ",
      "status": "UNVERIFIED",
      "source": "ISTM",
      "additionalProperties": {
        "competencyType": "Domain",
        "cod": "NPA",
        "competencyArea": "Management"
      }
    },
    {
      "type": "COMPETENCY",
      "id": "CID0367",
      "name": "Finishing Touch",
      "description": "Description for Competency",
      "status": "UNVERIFIED",
      "source": "ISTM",
      "bookmark": false,
      "additionalProperties": {
        "competencyType": "Behavioural",
        "cod": "Karmayogi Bharat",
        "competencyArea": "Political Sciences"
      }
    },
    {
      "type": "COMPETENCY",
      "id": "CID035",
      "name": "Design Thinking L4",
      "description": "Thinking Capability in a Design Process",
      "status": "UNVERIFIED",
      "source": "ISTM",
      "additionalProperties": {
        "competencyType": "Domain",
        "competencyArea": "Research and Development"
      }
    },
    {
      "type": "COMPETENCY",
      "id": "CID053",
      "name": "New Skills",
      "description": "Skilss",
      "status": "UNVERIFIED",
      "source": "asdasdasda",
      "additionalProperties": {
        "competencyType": "Behavioural"
      }
    },
    {
      "type": "COMPETENCY",
      "id": "CID059",
      "name": "Covid realted",
      "description": "this is realated to covid",
      "status": "UNVERIFIED",
      "source": "covid",
      "additionalProperties": {
        "competencyType": "Behavioural"
      }
    },
    {
      "type": "COMPETENCY",
      "id": "CID050",
      "name": "Exploring skills",
      "description": "Sample description",
      "status": "UNVERIFIED",
      "source": "Test source",
      "additionalProperties": {
        "competencyType": "Domain"
      }
    },
    {
      "type": "COMPETENCY",
      "id": "CID0208",
      "name": "Ruling",
      "description": "competency description",
      "status": "UNVERIFIED",
      "source": "ISTM",
      "reviewComments": "Reject 2",
      "additionalProperties": {
        "competencyType": "Behavioural",
        "cod": "",
        "competencyArea": "Level 1"
      }
    },
    {
      "type": "COMPETENCY",
      "id": "CID052",
      "name": "Leadership ",
      "description": "Leadership ",
      "status": "UNVERIFIED",
      "source": "ISTM",
      "additionalProperties": {
        "competencyType": "Behavioural",
        "cod": "iGOT"
      }
    },
    {
      "type": "COMPETENCY",
      "id": "CID0338",
      "name": "New Comp",
      "description": "des",
      "status": "UNVERIFIED",
      "source": "ISTM",
      "createdDate": "2021-02-05 06:33:04",
      "additionalProperties": {
        "competencyType": "Behavioural",
        "competencyArea": "Level 1",
        "cod": "NACIN"
      },
      "userInfo": {
        "sub": "a781bd01-1d72-4ee7-84cd-2e97eec520f8",
        "name": "Sakthivel Govindan",
        "email": "sakthivel.govindan@tarento.com"
      }
    },
    {
      "type": "COMPETENCY",
      "id": "CID070",
      "name": "RnD",
      "description": "RND",
      "status": "VERIFIED",
      "source": "ISTM",
      "additionalProperties": {
        "competencyType": "Functional"
      }
    },
    {
      "type": "COMPETENCY",
      "id": "CID048",
      "name": "Problem Solving",
      "description": "Special skill to solve the prrobelm",
      "status": "UNVERIFIED",
      "source": "ISTM",
      "additionalProperties": {
        "competencyType": "Behavioural",
        "cod": "NACIN",
        "competencyArea": "Social Studies"
      }
    },
    {
      "type": "COMPETENCY",
      "id": "CID041",
      "name": "Design Thinking L4",
      "description": "Thinking Capability in a Design Process",
      "status": "UNVERIFIED",
      "source": "ISTM",
      "additionalProperties": {
        "competencyType": "Domain",
        "cod": "All departments"
      }
    },
    {
      "type": "COMPETENCY",
      "id": "CID024",
      "name": "Design Thinking",
      "description": "Thinking Capability in a Design Process",
      "status": "VERIFIED",
      "source": "ISTM",
      "additionalProperties": {
        "competencyType": "Domain",
        "cod": "iGOT"
      }
    },
    {
      "type": "COMPETENCY",
      "id": "CID022",
      "name": "Documentation",
      "description": "Documentation techniques and prerequisites",
      "status": "VERIFIED",
      "source": "ISTM",
      "additionalProperties": {
        "competencyType": "Domain",
        "cod": "iGOT"
      }
    },
    {
      "type": "COMPETENCY",
      "id": "CID031",
      "name": "Design Thinking L2",
      "description": "Thinking Capability in a Design Process",
      "status": "UNVERIFIED",
      "source": "CBP Provider",
      "additionalProperties": {
        "competencyType": "Domain"
      }
    },
    {
      "type": "COMPETENCY",
      "id": "CID032",
      "name": "Design Thinking L3",
      "description": "Thinking Capability in a Design Process",
      "status": "UNVERIFIED",
      "source": "CBP Provider",
      "additionalProperties": {
        "competencyType": "Domain"
      }
    },
    {
      "type": "COMPETENCY",
      "id": "CID034",
      "name": "Design Thinking L4",
      "description": "Thinking Capability in a Design Process",
      "status": "UNVERIFIED",
      "source": "CBP Provider",
      "additionalProperties": {
        "competencyType": "Domain"
      }
    },
    {
      "type": "COMPETENCY",
      "id": "CID038",
      "name": "Design Thinking L5",
      "description": "Thinking Capability in a Design Process",
      "status": "UNVERIFIED",
      "source": "CBP Provider",
      "additionalProperties": {
        "competencyType": "Domain"
      }
    },
    {
      "type": "COMPETENCY",
      "id": "CID040",
      "name": "Design Thinking L4",
      "description": "Thinking Capability in a Design Process",
      "status": "UNVERIFIED",
      "source": "CBP Provider",
      "additionalProperties": {
        "competencyType": "Domain"
      }
    },
    {
      "type": "COMPETENCY",
      "id": "CID042",
      "name": "Design Thinking L4",
      "description": "Thinking Capability in a Design Process",
      "status": "UNVERIFIED",
      "source": "CBP Provider",
      "additionalProperties": {
        "competencyType": "Domain"
      }
    },
    {
      "type": "COMPETENCY",
      "id": "CID037",
      "name": "Design Thinking",
      "description": "Thinking Capability in a Design Process",
      "status": "UNVERIFIED",
      "source": "CBP Provider",
      "additionalProperties": {
        "competencyType": "Domain"
      }
    },
    {
      "type": "COMPETENCY",
      "id": "CID011",
      "name": "Conceptual Thinking",
      "description": "Control project plans to manage project schedule and deliverables",
      "status": "VERIFIED",
      "source": "ISTM",
      "additionalProperties": {
        "competencyType": "Behavioural"
      }
    },
    {
      "type": "COMPETENCY",
      "id": "CID04",
      "name": "Project Administration",
      "description": "Creating a Work Breakdown Structure.",
      "status": "UNVERIFIED",
      "source": "ISTM",
      "additionalProperties": {
        "competencyType": "Functional"
      }
    },
    {
      "type": "COMPETENCY",
      "id": "CID069",
      "name": "RnD",
      "description": "Research and Development",
      "status": "UNVERIFIED",
      "source": "ISTM",
      "additionalProperties": {
        "competencyType": "Functional"
      }
    },
    {
      "type": "COMPETENCY",
      "id": "CID0217",
      "name": "Negotiate",
      "description": "skill description",
      "status": "UNVERIFIED",
      "source": "ISTM",
      "additionalProperties": {
        "competencyType": "Domain",
        "cod": "iGOT",
        "competencyArea": "Management"
      }
    },
    {
      "type": "COMPETENCY",
      "id": "CID023",
      "name": "Design of Civic Bodies",
      "description": "Designing the Civic Bodies and their structuring",
      "status": "REJECTED",
      "source": "CBP Provider",
      "reviewComments": "rejecting node",
      "additionalProperties": {
        "competencyType": "Domain"
      }
    },
    {
      "type": "COMPETENCY",
      "id": "CID051",
      "name": "Decision making",
      "description": "Decision making Dec",
      "status": "UNVERIFIED",
      "source": "Decision making Source",
      "additionalProperties": {
        "competencyType": "Behavioural"
      }
    },
    {
      "type": "COMPETENCY",
      "id": "CID0267",
      "name": "Mechanical",
      "description": "descirption",
      "status": "UNVERIFIED",
      "source": "ISTM",
      "createdDate": "2021-02-02 05:01:08",
      "additionalProperties": {
        "competencyType": "Behavioural",
        "competencyArea": "Level 1",
        "cod": "NPA"
      },
      "userInfo": {
        "sub": "a781bd01-1d72-4ee7-84cd-2e97eec520f8",
        "name": "Sakthivel Govindan",
        "email": "sakthivel.govindan@tarento.com"
      }
    },
    {
      "type": "COMPETENCY",
      "id": "CID0252",
      "name": "Finance",
      "description": "description",
      "status": "UNVERIFIED",
      "source": "ISTM",
      "createdDate": "2021-02-02 04:10:17",
      "additionalProperties": {
        "competencyType": "Behavioural",
        "competencyArea": "Management",
        "cod": "NPA"
      },
      "userInfo": {
        "sub": "a781bd01-1d72-4ee7-84cd-2e97eec520f8",
        "name": "Sakthivel Govindan",
        "email": "sakthivel.govindan@tarento.com"
      }
    },
    {
      "type": "COMPETENCY",
      "id": "CID0341",
      "name": "comp two",
      "description": "description",
      "status": "UNVERIFIED",
      "source": "ISTM",
      "createdDate": "2021-02-08 05:14:21",
      "additionalProperties": {
        "competencyType": "Behavioural",
        "competencyArea": "Test 2563",
        "cod": "NPA"
      },
      "userInfo": {
        "sub": "a781bd01-1d72-4ee7-84cd-2e97eec520f8",
        "name": "Sakthivel Govindan",
        "email": "sakthivel.govindan@tarento.com"
      }
    },
    {
      "type": "COMPETENCY",
      "id": "CID0350",
      "name": "Testing",
      "description": "description",
      "status": "UNVERIFIED",
      "source": "ISTM",
      "createdDate": "2021-02-09 08:25:10",
      "additionalProperties": {
        "competencyType": "Behavioural",
        "competencyArea": "Level 1",
        "cod": "iGOT"
      },
      "userInfo": {
        "sub": "a781bd01-1d72-4ee7-84cd-2e97eec520f8",
        "name": "Sakthivel Govindan",
        "email": "sakthivel.govindan@tarento.com"
      }
    },
    {
      "type": "COMPETENCY",
      "id": "CID0223",
      "name": "Develop",
      "description": "description-",
      "status": "UNVERIFIED",
      "source": "ISTM",
      "createdDate": "2021-01-25 13:57:03",
      "additionalProperties": {
        "competencyType": "Behavioural",
        "competencyArea": "Competency Area",
        "cod": "iGOT"
      },
      "userInfo": {
        "sub": "147cc15f-8c2b-4e5b-9059-8e1a837e8a5d",
        "name": "Rangabashyam",
        "email": "rangabashyam.krishnamachari@tarento.com"
      }
    },
    {
      "type": "COMPETENCY",
      "id": "CID002",
      "name": "Documentation skill",
      "description": "description",
      "status": "REJECTED",
      "source": "ISTM",
      "reviewComments": "duplicated",
      "createdDate": "2021-02-23 07:25:04",
      "additionalProperties": {
        "competencyType": "Behavioural",
        "cod": "Karmayogi Bharat",
        "competencyArea": "Political Sciences"
      },
      "userInfo": {
        "sub": "f:923bdc18-520d-48d4-a84e-3cde1e655ebd:f1cbd741-47ac-4b33-b4c4-fe0aeb861819",
        "name": "Sakthivel Govindan",
        "email": "sakthivel.govindan@tarento.com"
      }
    },
    {
      "type": "COMPETENCY",
      "id": "CID02",
      "name": "Teaching",
      "description": "Description",
      "status": "UNVERIFIED",
      "source": "ISTM",
      "additionalProperties": {
        "competencyType": "Behavioural"
      }
    },
    {
      "type": "COMPETENCY",
      "id": "CID0246",
      "name": "Explore ",
      "description": "cmp descrp",
      "status": "UNVERIFIED",
      "source": "ISTM",
      "additionalProperties": {
        "competencyType": "Behavioural",
        "cod": "iGOT",
        "competencyArea": "Management"
      }
    },
    {
      "type": "COMPETENCY",
      "id": "CID049",
      "name": "Handling data",
      "description": "Description",
      "status": "REJECTED",
      "source": "ISTM",
      "additionalProperties": {
        "competencyType": "Domain",
        "cod": "iGOT"
      }
    },
    {
      "type": "COMPETENCY",
      "id": "CID060",
      "name": "Design Thinking L6",
      "description": "Thinking Capability in a Design Process",
      "status": "UNVERIFIED",
      "source": "CBP Provider",
      "additionalProperties": {
        "competencyType": "Domain"
      }
    },
    {
      "type": "COMPETENCY",
      "id": "CID054",
      "name": "Communications",
      "description": "Commuication skills",
      "status": "UNVERIFIED",
      "source": "source",
      "additionalProperties": {
        "competencyType": "Behavioural"
      }
    },
    {
      "type": "COMPETENCY",
      "id": "CID055",
      "name": "Excellence",
      "description": "Excellence skills",
      "status": "UNVERIFIED",
      "source": "test   source",
      "additionalProperties": {
        "competencyType": "Behavioural"
      }
    },
    {
      "type": "COMPETENCY",
      "id": "CID030",
      "name": "Design Thinking L1",
      "description": "Thinking Capability in a Design Process",
      "status": "UNVERIFIED",
      "source": "CBP Provider",
      "additionalProperties": {
        "competencyType": "Domain"
      }
    },
    {
      "type": "COMPETENCY",
      "id": "CID043",
      "name": "Design Thinking L4",
      "description": "Thinking Capability in a Design Process",
      "status": "UNVERIFIED",
      "source": "CBP Provider",
      "additionalProperties": {
        "competencyType": "Domain"
      }
    },
    {
      "type": "COMPETENCY",
      "id": "CID044",
      "name": "Design Thinking L4",
      "description": "Thinking Capability in a Design Process",
      "status": "UNVERIFIED",
      "source": "CBP Provider",
      "additionalProperties": {
        "competencyType": "Domain"
      }
    },
    {
      "type": "COMPETENCY",
      "id": "CID025",
      "name": "Design Thinking",
      "description": "Thinking Capability in a Design Process",
      "status": "UNVERIFIED",
      "source": "CBP Provider",
      "additionalProperties": {
        "competencyType": "Domain"
      }
    },
    {
      "type": "COMPETENCY",
      "id": "CID026",
      "name": "Design Thinking II",
      "description": "Thinking Capability in a Design Process",
      "status": "UNVERIFIED",
      "source": "ISTM",
      "additionalProperties": {
        "competencyType": "Domain"
      }
    },
    {
      "type": "COMPETENCY",
      "id": "CID036",
      "name": "Design Thinking L4",
      "description": "Thinking Capability in a Design Process",
      "status": "REJECTED",
      "source": "CBP Provider",
      "reviewComments": "reject",
      "additionalProperties": {
        "competencyType": "Domain"
      }
    },
    {
      "type": "COMPETENCY",
      "id": "CID0253",
      "name": "Office work",
      "description": "description",
      "status": "UNVERIFIED",
      "source": "ISTM",
      "createdDate": "2021-02-02 04:12:18",
      "additionalProperties": {
        "competencyType": "Behavioural",
        "competencyArea": "Level 1",
        "cod": "NPA"
      },
      "userInfo": {
        "sub": "a781bd01-1d72-4ee7-84cd-2e97eec520f8",
        "name": "Sakthivel Govindan",
        "email": "sakthivel.govindan@tarento.com"
      }
    },
    {
      "type": "COMPETENCY",
      "id": "CID0348",
      "name": "Comp-six",
      "description": "description",
      "status": "UNVERIFIED",
      "source": "ISTM",
      "createdDate": "2021-02-08 12:25:31",
      "additionalProperties": {
        "competencyType": "Behavioural",
        "competencyArea": "Political Sciences",
        "cod": "NACIN"
      },
      "userInfo": {
        "sub": "a781bd01-1d72-4ee7-84cd-2e97eec520f8",
        "name": "Sakthivel Govindan",
        "email": "sakthivel.govindan@tarento.com"
      }
    },
    {
      "type": "COMPETENCY",
      "id": "CID057",
      "name": "New Functional request test",
      "description": "Test functional ",
      "status": "UNVERIFIED",
      "source": "Test Source",
      "additionalProperties": {
        "competencyType": "Functional",
        "competencyArea": "Ethical values"
      }
    },
    {
      "type": "COMPETENCY",
      "id": "CID033",
      "name": "Design Thinking L4",
      "description": "Thinking Capability in a Design Process",
      "status": "UNVERIFIED",
      "source": "CBP Provider",
      "additionalProperties": {
        "competencyType": "Domain"
      }
    },
    {
      "type": "COMPETENCY",
      "id": "CID028",
      "name": "Thinking Capability",
      "description": "Thinking Capability in Engineering Process",
      "status": "VERIFIED",
      "source": "CBP Provider",
      "additionalProperties": {
        "competencyType": "Domain"
      }
    },
    {
      "type": "COMPETENCY",
      "id": "CID027",
      "name": "Design Thinking",
      "description": "Thinking Capability in a Design Process",
      "status": "UNVERIFIED",
      "source": "CBP Provider",
      "additionalProperties": {
        "competencyType": "Domain"
      }
    },
    {
      "type": "COMPETENCY",
      "id": "CID056",
      "name": "Domain Gathering",
      "description": "Domain Knowledge",
      "status": "UNVERIFIED",
      "source": "Domain Source",
      "additionalProperties": {
        "competencyType": "Behavioural"
      }
    },
    {
      "type": "COMPETENCY",
      "id": "CID072",
      "name": "Experienced Competency",
      "description": "Level of Experience",
      "status": "UNVERIFIED",
      "source": "ISTM",
      "additionalProperties": {
        "competencyType": "Domain"
      }
    },
    {
      "type": "COMPETENCY",
      "id": "CID073",
      "name": "Law",
      "description": "This is for testing",
      "status": "UNVERIFIED",
      "source": "ISTM",
      "additionalProperties": {
        "competencyType": "Behavioural"
      }
    },
    {
      "type": "COMPETENCY",
      "id": "CID063",
      "name": "Presentation skills",
      "description": "Presentation skill is the way in which an individual is able to put forward the work that is done by them.",
      "status": "UNVERIFIED",
      "source": "ISTM",
      "additionalProperties": {
        "competencyType": "",
        "competencyArea": "Political Sciences"
      }
    },
    {
      "type": "COMPETENCY",
      "id": "CID0368",
      "name": "Lecture",
      "description": "description",
      "status": "UNVERIFIED",
      "source": "ISTM",
      "createdDate": "2021-02-12 06:52:14",
      "additionalProperties": {
        "competencyType": "Behavioural",
        "competencyArea": "Management",
        "cod": "HR"
      },
      "userInfo": {
        "sub": "a781bd01-1d72-4ee7-84cd-2e97eec520f8",
        "name": "Sakthivel Govindan",
        "email": "sakthivel.govindan@tarento.com"
      }
    },
    {
      "type": "COMPETENCY",
      "id": "CID0345",
      "name": "comp five",
      "description": "description check one",
      "status": "REJECTED",
      "source": "ISTM",
      "reviewComments": "Reject",
      "createdDate": "2021-02-08 05:43:18",
      "additionalProperties": {
        "competencyType": "Behavioural",
        "competencyArea": "Political Sciences",
        "cod": "NPA"
      },
      "userInfo": {
        "sub": "a781bd01-1d72-4ee7-84cd-2e97eec520f8",
        "name": "Sakthivel Govindan",
        "email": "sakthivel.govindan@tarento.com"
      }
    },
    {
      "type": "COMPETENCY",
      "id": "CID0344",
      "name": "Investigation",
      "description": "Project management is the application of processes, methods, skills, knowledge and experience to achieve specific project objectives according to the project acceptance criteria within agreed parameters.",
      "status": "VERIFIED",
      "source": "ISTM",
      "createdDate": "2021-02-08 05:20:32",
      "additionalProperties": {
        "competencyType": "Functional",
        "competencyArea": "Management",
        "cod": ""
      },
      "userInfo": {
        "sub": "dc15a3af-345a-4355-9ca1-9151e9704f88",
        "name": "Bhakti Mohapatra",
        "email": "bhakti.mohapatra@tarento.com"
      }
    }
  ]
}